diagmap.py
diagmap-1.3.dist-info/LICENSE.txt
diagmap-1.3.dist-info/METADATA
diagmap-1.3.dist-info/WHEEL
diagmap-1.3.dist-info/top_level.txt
diagmap-1.3.dist-info/RECORD
