Metadata-Version: 2.1
Name: diagmap
Version: 1.3
Summary: Diagnostic mapping utility
Home-page: https://github.com/alexrobomind/diagmap
Author: Alexander Knieps
Author-email: a.knieps@fz-juelich.de
License: BSD-2-Clause
Platform: UNKNOWN
Requires-Dist: networkx (>=2.4)
Requires-Dist: numpy (>=1.18.5)
Requires-Dist: tqdm (>=4.49.0)
Requires-Dist: scipy (>=1.4.1)
